{
  "path": "/documentation/coretelephony/ctcellularplanprovisioningrequest",
  "type": "Class",
  "name": "CTCellularPlanProvisioningRequest",
  "desc": "A request specifying an eSIM to download and install.",
  "items": [
    {
      "name": "var address: String",
      "desc": "The address of the carrier network’s eSIM server."
    },
    {
      "name": "var confirmationCode: String?",
      "desc": "The provisioning request’s confirmation code, provided by the network operator when initiating an eSIM download."
    },
    {
      "name": "var eid: String?",
      "desc": "The provisioning request’s eUICC identifier (EID)."
    },
    {
      "name": "var iccid: String?",
      "desc": "The provisioning request’s Integrated Circuit Card Identifier (ICCID)."
    },
    {
      "name": "var matchingID: String?",
      "desc": "The provisioning request’s matching identifier (MatchingID)."
    },
    {
      "name": "var oid: String?",
      "desc": "The provisioning request’s Object Identifier (OID)."
    }
  ],
  "declaration": "class CTCellularPlanProvisioningRequest : NSObject",
  "inheritsFrom": [
    "NSObject"
  ],
  "conformsTo": [
    "NSSecureCoding"
  ]
}