{
  "path": "/documentation/foundation/nsspellserverdelegate/1410726-spellserver",
  "type": "Instance Method",
  "name": "spellServer(_:suggestGuessesForWord:inLanguage:)",
  "desc": "Gives the delegate the opportunity to suggest guesses to the sender for the correct spelling of the given misspelled word in the specified language.",
  "items": [],
  "declaration": "optional func spellServer(_ sender: NSSpellServer, \n    suggestGuessesForWord word: String, \n               inLanguage language: String) -> [String]?"
}