{
  "path": "/documentation/SwiftUI/Gradient",
  "type": "Structure",
  "name": "Gradient",
  "desc": "A color gradient represented as an array of color stops, each having a parametric location value.",
  "items": [
    {
      "name": "init(colors: [Color])",
      "desc": "Creates a gradient from an array of colors."
    },
    {
      "name": "init(stops: [Gradient.Stop])",
      "desc": "Creates a gradient from an array of color stops."
    },
    {
      "name": "var stops: [Gradient.Stop]",
      "desc": "The array of color stops."
    },
    {
      "name": "struct Stop",
      "desc": "One color stop in the gradient."
    },
    {
      "name": "static func == (Gradient, Gradient) -> Bool",
      "desc": "Indicates whether two gradients are equal."
    },
    {
      "name": "static func != (Self, Self) -> Bool",
      "desc": "Indicates whether two gradients are unequal."
    }
  ],
  "declaration": "@frozen struct Gradient",
  "conformsTo": [
    "Equatable"
  ]
}