{
  "path": "/documentation/speech/sfspeechrecognizerauthorizationstatus",
  "type": "Enumeration",
  "name": "SFSpeechRecognizerAuthorizationStatus",
  "desc": "The app's authorization to perform speech recognition.",
  "items": [
    {
      "name": "case notDetermined",
      "desc": "The app's authorization status has not yet been determined."
    },
    {
      "name": "case denied",
      "desc": "The user denied your app's request to perform speech recognition."
    },
    {
      "name": "case restricted",
      "desc": "The device prevents your app from performing speech recognition."
    },
    {
      "name": "case authorized",
      "desc": "The user granted your app's request to perform speech recognition."
    }
  ],
  "declaration": "enum SFSpeechRecognizerAuthorizationStatus : Int, @unchecked Sendable",
  "conformsTo": [
    "Sendable"
  ]
}