{
  "path": "/documentation/coreimage/cicontextoption",
  "type": "Structure",
  "name": "CIContextOption",
  "desc": "No overview available.",
  "items": [
    {
      "name": "init(rawValue: String)"
    },
    {
      "name": "static let allowLowPower: CIContextOption"
    },
    {
      "name": "static let cacheIntermediates: CIContextOption",
      "desc": "An option for whether the context caches the contents of any intermediate pixel buffers it uses during rendering."
    },
    {
      "name": "static let highQualityDownsample: CIContextOption",
      "desc": "An option controlling the quality of image downsampling operations performed by the context."
    },
    {
      "name": "static let name: CIContextOption"
    },
    {
      "name": "static let outputColorSpace: CIContextOption",
      "desc": "A key for the color space to use for images before they are rendered to the context."
    },
    {
      "name": "static let outputPremultiplied: CIContextOption",
      "desc": "An option for whether output rendering by the context produces alpha-premultiplied pixels."
    },
    {
      "name": "static let priorityRequestLow: CIContextOption",
      "desc": "A key for enabling low-priority GPU use."
    },
    {
      "name": "static let useSoftwareRenderer: CIContextOption",
      "desc": "A key for enabling software renderer use. If the associated NSNumber object is true, the software renderer is required."
    },
    {
      "name": "static let workingColorSpace: CIContextOption",
      "desc": "A key for the color space to use for image operations."
    },
    {
      "name": "static let workingFormat: CIContextOption",
      "desc": "An option for the color format to use for intermediate results when rendering with the context."
    }
  ],
  "declaration": "struct CIContextOption, @unchecked Sendable",
  "conformsTo": [
    "Equatable",
    "Hashable",
    "RawRepresentable",
    "Sendable"
  ]
}