{
  "path": "/documentation/coremedia/cmmediatype",
  "type": "Type Alias",
  "name": "CMMediaType",
  "desc": "A media type.",
  "items": [
    {
      "name": "var kCMMediaType_Video: CMMediaType",
      "desc": "Video media."
    },
    {
      "name": "var kCMMediaType_Audio: CMMediaType",
      "desc": "Audio media."
    },
    {
      "name": "var kCMMediaType_Muxed: CMMediaType",
      "desc": "Muxed media."
    },
    {
      "name": "var kCMMediaType_Text: CMMediaType",
      "desc": "Text media."
    },
    {
      "name": "var kCMMediaType_ClosedCaption: CMMediaType",
      "desc": "Closed-caption media."
    },
    {
      "name": "var kCMMediaType_Subtitle: CMMediaType",
      "desc": "Subtitle media."
    },
    {
      "name": "var kCMMediaType_TimeCode: CMMediaType",
      "desc": "Time code media."
    },
    {
      "name": "var kCMMediaType_Metadata: CMMediaType",
      "desc": "Meta data."
    }
  ],
  "declaration": "typealias CMMediaType = FourCharCode"
}