{
  "path": "/documentation/security/authorizationexternalform",
  "type": "Structure",
  "name": "AuthorizationExternalForm",
  "desc": "The external representation of an authorization reference.",
  "items": [
    {
      "name": "init()"
    },
    {
      "name": "init(bytes: (CChar, CChar, CChar, CChar, CChar, CChar, CChar, CChar, CChar, CChar, CChar, CChar, CChar, CChar, CChar, CChar, CChar, CChar, CChar, CChar, CChar, CChar, CChar, CChar, CChar, CChar, CChar, CChar, CChar, CChar, CChar, CChar))"
    },
    {
      "name": "var bytes: (CChar, CChar, CChar, CChar, CChar, CChar, CChar, CChar, CChar, CChar, CChar, CChar, CChar, CChar, CChar, CChar, CChar, CChar, CChar, CChar, CChar, CChar, CChar, CChar, CChar, CChar, CChar, CChar, CChar, CChar, CChar, CChar)",
      "desc": "An array of characters representing the external form of an authorization reference."
    }
  ],
  "declaration": "struct AuthorizationExternalForm"
}