{
  "path": "/documentation/sirikit/insendmessagerecipientunsupportedreason",
  "type": "Enumeration",
  "name": "INSendMessageRecipientUnsupportedReason",
  "desc": "Constants indicating the reason why a recipient is not supported.",
  "items": [
    {
      "name": "case noAccount",
      "desc": "A recipient without an account."
    },
    {
      "name": "case offline",
      "desc": "An offline recipient."
    },
    {
      "name": "case messagingServiceNotEnabledForRecipient",
      "desc": "A recipient for whom messaging is not enabled."
    },
    {
      "name": "case noHandleForLabel",
      "desc": "A recipient for whom there is no handle for the provided label."
    },
    {
      "name": "case noValidHandle",
      "desc": "A recipient for whom there is no valid handle."
    },
    {
      "name": "case requestedHandleInvalid",
      "desc": "A recipient for whom the requested handle is invalid."
    }
  ],
  "declaration": "enum INSendMessageRecipientUnsupportedReason : Int, @unchecked Sendable",
  "conformsTo": [
    "Sendable"
  ]
}