{
  "path": "/documentation/screentime/stwebhistory",
  "type": "Class",
  "name": "STWebHistory",
  "desc": "The object you use to delete web-usage data.",
  "items": [
    {
      "name": "init(bundleIdentifier: String)",
      "desc": "Creates a web history instance to delete web-usage data associated to the bundle identifier you specify."
    },
    {
      "name": "func deleteAllHistory()",
      "desc": "Deletes all web history associated with the bundle identifier you specified during initialization."
    },
    {
      "name": "func deleteHistory(during: DateInterval)",
      "desc": "Deletes web history that occurred during the date interval you specify."
    },
    {
      "name": "func deleteHistory(for: URL)",
      "desc": "Deletes all the web history for the URL you specify."
    }
  ],
  "declaration": "class STWebHistory : NSObject",
  "inheritsFrom": [
    "NSObject"
  ]
}