{
  "path": "/documentation/swiftui/longpressgesture",
  "type": "Structure",
  "name": "LongPressGesture",
  "desc": "A gesture that succeeds when the user performs a long press.",
  "items": [
    {
      "name": "init(minimumDuration: Double)",
      "desc": "Creates a long-press gesture with a minimum duration"
    },
    {
      "name": "init(minimumDuration: Double, maximumDistance: CGFloat)",
      "desc": "Creates a long-press gesture with a minimum duration and a maximum distance that the interaction can move before the gesture fails."
    },
    {
      "name": "var minimumDuration: Double",
      "desc": "The minimum duration of the long press that must elapse before the gesture succeeds."
    },
    {
      "name": "var maximumDistance: CGFloat",
      "desc": "The maximum distance that the long press can move before the gesture fails."
    },
    {
      "name": "typealias Body",
      "desc": "The type of gesture representing the body of Self."
    },
    {
      "name": "typealias Value",
      "desc": "The type representing the gesture’s value."
    }
  ],
  "declaration": "struct LongPressGesture",
  "conformsTo": [
    "Gesture"
  ]
}