{
  "path": "/documentation/appkit/nsaccessibilitycustomaction",
  "type": "Class",
  "name": "NSAccessibilityCustomAction",
  "desc": "A custom action to perform on an accessible object.",
  "items": [
    {
      "name": "init(name: String, handler: (() -> Bool)?)",
      "desc": "Creates a custom action object with the specified name and handler."
    },
    {
      "name": "init(name: String, target: NSObjectProtocol, selector: Selector)",
      "desc": "Creates a custom action object with the specified name, target, and selector."
    },
    {
      "name": "var name: String",
      "desc": "A localized name that describes the action."
    },
    {
      "name": "var handler: (() -> Bool)?",
      "desc": "The closure that handles the execution of the action."
    },
    {
      "name": "var target: NSObjectProtocol?",
      "desc": "The object that performs the action through a selector."
    },
    {
      "name": "var selector: Selector?",
      "desc": "The method to call on the target to perform the action."
    }
  ],
  "declaration": "class NSAccessibilityCustomAction : NSObject",
  "inheritsFrom": [
    "NSObject"
  ]
}