{
  "path": "/documentation/sirikit/instartphotoplaybackintenthandling/1906885-resolvealbumname",
  "type": "Instance Method",
  "name": "resolveAlbumName(for:with:)",
  "desc": "Resolves the name of the photo album containing the photos.DeprecatedThis intent is no longer available. You may define a custom intent instead. For more information, see Deprecated SiriKit Intent Domains.",
  "items": [],
  "declaration": "optional func resolveAlbumName(for intent: INStartPhotoPlaybackIntent, \n                          with completion: @escaping (INStringResolutionResult) -> Void)"
}