{
  "path": "/documentation/homekit/hmeventtriggeractivationstate",
  "type": "Enumeration",
  "name": "HMEventTriggerActivationState",
  "desc": "The activation state of an event trigger.",
  "items": [
    {
      "name": "case disabled",
      "desc": "Trigger is not activated."
    },
    {
      "name": "case disabledNoCompatibleHomeHub",
      "desc": "Trigger is not active because there is no compatible home hub."
    },
    {
      "name": "case disabledNoHomeHub",
      "desc": "Trigger is not active because there is no home hub."
    },
    {
      "name": "case disabledNoLocationServicesAuthorization",
      "desc": "Trigger is not active because the user has not authorized use of location services."
    },
    {
      "name": "case enabled",
      "desc": "The trigger is currently active."
    }
  ],
  "declaration": "enum HMEventTriggerActivationState : UInt, @unchecked Sendable",
  "conformsTo": [
    "Sendable"
  ]
}