{
  "path": "/documentation/kernel/iohipointing",
  "type": "Class",
  "name": "IOHIPointing",
  "desc": "No overview available.",
  "items": [
    {
      "name": "- buttonCount"
    },
    {
      "name": "- close"
    },
    {
      "name": "- copyAccelerationTable"
    },
    {
      "name": "- copyScrollAccelerationTable"
    },
    {
      "name": "- copyScrollAccelerationTableForType"
    },
    {
      "name": "- dispatchAbsolutePointerEvent"
    },
    {
      "name": "- dispatchRelativePointerEvent"
    },
    {
      "name": "- dispatchScrollWheelEvent"
    },
    {
      "name": "- dispatchScrollWheelEventWithAccelInfo"
    },
    {
      "name": "- free"
    },
    {
      "name": "- getMetaClass"
    },
    {
      "name": "- getPointingMode"
    },
    {
      "name": "- getScrollType"
    },
    {
      "name": "- hidKind"
    },
    {
      "name": "- init"
    },
    {
      "name": "- message"
    },
    {
      "name": "- open"
    },
    {
      "name": "- open"
    },
    {
      "name": "- powerStateDidChangeTo"
    },
    {
      "name": "- powerStateWillChangeTo"
    },
    {
      "name": "- resetPointer"
    },
    {
      "name": "- resetScroll"
    },
    {
      "name": "- resolution"
    },
    {
      "name": "- scalePointer"
    },
    {
      "name": "- scrollReportRate"
    },
    {
      "name": "- scrollResolutionForType"
    },
    {
      "name": "- setParamProperties"
    },
    {
      "name": "- setPointingMode"
    },
    {
      "name": "- setScrollType"
    },
    {
      "name": "- setupForAcceleration"
    },
    {
      "name": "- setupScrollForAcceleration"
    },
    {
      "name": "- start"
    },
    {
      "name": "- updateProperties"
    }
  ],
  "declaration": "class IOHIPointing : IOHIDevice",
  "inheritsFrom": [
    "IOHIDevice"
  ]
}