{
  "path": "/documentation/storekit/skproductdiscount",
  "type": "Class",
  "name": "SKProductDiscount",
  "desc": "The details of an introductory offer or a promotional offer for an auto-renewable subscription.",
  "items": [
    {
      "name": "var identifier: String?",
      "desc": "A string used to uniquely identify a discount offer for a product."
    },
    {
      "name": "var type: SKProductDiscount.`Type`",
      "desc": "The type of discount offer."
    },
    {
      "name": "enum SKProductDiscount.Type",
      "desc": "Values representing the types of discount offers an app can present."
    },
    {
      "name": "var price: NSDecimalNumber",
      "desc": "The discount price of the product in the local currency."
    },
    {
      "name": "var priceLocale: Locale",
      "desc": "The locale used to format the discount price of the product."
    },
    {
      "name": "var paymentMode: SKProductDiscount.PaymentMode",
      "desc": "The payment mode for this product discount."
    },
    {
      "name": "enum SKProductDiscount.PaymentMode",
      "desc": "Values representing the payment modes for a product discount."
    },
    {
      "name": "var numberOfPeriods: Int",
      "desc": "An integer that indicates the number of periods the product discount is available."
    },
    {
      "name": "var subscriptionPeriod: SKProductSubscriptionPeriod",
      "desc": "An object that defines the period for the product discount."
    }
  ],
  "declaration": "class SKProductDiscount : NSObject",
  "inheritsFrom": [
    "NSObject"
  ]
}