{
  "path": "/documentation/sensorkit/srfetchrequest",
  "type": "Class",
  "name": "SRFetchRequest",
  "desc": "An object that defines the criteria for a sample query.",
  "items": [
    {
      "name": "var device: SRDevice",
      "desc": "The device to query for sample data."
    },
    {
      "name": "class SRDevice",
      "desc": "A representation of a device that provides sample data."
    },
    {
      "name": "var from: SRAbsoluteTime",
      "desc": "Fetches sample information that occurs after this time."
    },
    {
      "name": "var to: SRAbsoluteTime",
      "desc": "Fetches sample information that occurs before this time."
    },
    {
      "name": "struct SRAbsoluteTime",
      "desc": "A value that describes when the system records the data."
    },
    {
      "name": "static func current() -> SRAbsoluteTime",
      "desc": "Provides the current absolute time."
    },
    {
      "name": "static func fromCFAbsoluteTime(_cf: CFAbsoluteTime) -> SRAbsoluteTime",
      "desc": "Provides an absolute time equivalent to the argument core-foundation absolute time."
    },
    {
      "name": "static func fromContinuousTime(_continuous: UInt64) -> SRAbsoluteTime",
      "desc": "Provides an absolute time equivalent to the argument continuous time."
    },
    {
      "name": "func toCFAbsoluteTime() -> CFAbsoluteTime",
      "desc": "Converts an absolute time to a core-foundation absolute time."
    }
  ],
  "declaration": "class SRFetchRequest : NSObject",
  "inheritsFrom": [
    "NSObject"
  ]
}