{
  "path": "/documentation/avfoundation/avplayer/hdrmode",
  "type": "Structure",
  "name": "AVPlayer.HDRMode",
  "desc": "A bitfield type that specifies an HDR mode.",
  "items": [
    {
      "name": "static var hlg: AVPlayer.HDRMode",
      "desc": "The Hybrid Log-Gamma HDR mode is available."
    },
    {
      "name": "static var hdr10: AVPlayer.HDRMode",
      "desc": "The HDR10 HDR mode is available."
    },
    {
      "name": "static var dolbyVision: AVPlayer.HDRMode",
      "desc": "The Dolby Vision HDR mode is available."
    },
    {
      "name": "init(rawValue: Int)",
      "desc": "Creates an HDR mode with a string value."
    }
  ],
  "declaration": "struct HDRMode, @unchecked Sendable",
  "conformsTo": [
    "OptionSet",
    "Sendable"
  ]
}