{
  "path": "/documentation/mapkit/mklocalsearch/request",
  "type": "Class",
  "name": "MKLocalSearch.Request",
  "desc": "The parameters to use when searching for points of interest on the map.",
  "items": [
    {
      "name": "init()",
      "desc": "Initializes a local search request."
    },
    {
      "name": "init(completion: MKLocalSearchCompletion)",
      "desc": "Initializes and returns a search request based on the specified search completion data."
    },
    {
      "name": "var naturalLanguageQuery: String?",
      "desc": "A string containing the desired search item."
    },
    {
      "name": "var region: MKCoordinateRegion",
      "desc": "A map region that provides a hint as to where to search."
    },
    {
      "name": "var pointOfInterestFilter: MKPointOfInterestFilter?",
      "desc": "A filter that lists point of interest categories to include or exclude in search results."
    },
    {
      "name": "var resultTypes: MKLocalSearch.ResultType",
      "desc": "The types of items to include in the search results."
    },
    {
      "name": "typealias MKLocalSearch.Request.ResultType",
      "desc": "Options that indicate types of search results."
    }
  ],
  "declaration": "class Request : NSObject",
  "inheritsFrom": [
    "NSObject"
  ],
  "conformsTo": [
    "NSCopying"
  ]
}