{
  "path": "/documentation/appkit/nseditor",
  "type": "Protocol",
  "name": "NSEditor",
  "desc": "No overview available.",
  "items": [
    {
      "name": "func commitEditing() -> Bool"
    },
    {
      "name": "func commitEditing(withDelegate: Any?, didCommit: Selector?, contextInfo: UnsafeMutableRawPointer?)"
    },
    {
      "name": "func commitEditingWithoutPresentingError()"
    },
    {
      "name": "func discardEditing()"
    }
  ],
  "declaration": "protocol NSEditor",
  "inheritsFrom": [
    "NSObjectProtocol"
  ]
}