{
  "path": "/documentation/sirikit/inappendtonoteintenthandling/2873748-confirm",
  "type": "Instance Method",
  "name": "confirm(intent:completion:)",
  "desc": "Confirms whether you can append content to the note.DeprecatedThis intent is no longer available. You may define a custom intent instead. For more information, see Deprecated SiriKit Intent Domains.",
  "items": [],
  "declaration": "optional func confirm(intent: INAppendToNoteIntent, \n           completion: @escaping (INAppendToNoteIntentResponse) -> Void)"
}