{
  "path": "/documentation/appkit/nssharingservicepicker",
  "type": "Class",
  "name": "NSSharingServicePicker",
  "desc": "A list of sharing services from which the user can choose.",
  "items": [
    {
      "name": "init(items: [Any])",
      "desc": "Initializes a new sharing service picker for the selected items."
    },
    {
      "name": "func show(relativeTo: NSRect, of: NSView, preferredEdge: NSRectEdge)",
      "desc": "Shows the picker, populated with sharing services related to the instance items."
    },
    {
      "name": "var delegate: NSSharingServicePickerDelegate?",
      "desc": "Specifies the service picker delegate."
    }
  ],
  "declaration": "class NSSharingServicePicker : NSObject",
  "inheritsFrom": [
    "NSObject"
  ]
}