{
  "path": "/documentation/uikit/uinib",
  "type": "Class",
  "name": "UINib",
  "desc": "An object that contains Interface Builder nib files.",
  "items": [
    {
      "name": "init(nibName: String, bundle: Bundle?)",
      "desc": "Returns a nib object from the nib file in the specified bundle."
    },
    {
      "name": "init(data: Data, bundle: Bundle?)",
      "desc": "Creates a nib object from nib data stored in memory."
    },
    {
      "name": "func instantiate(withOwner: Any?, options: [UINib.OptionsKey : Any]?) -> [Any]",
      "desc": "Unarchives and instantiates the in-memory contents of the nib object’s nib file, creating a distinct object tree and set of top-level objects."
    },
    {
      "name": "struct UINib.OptionsKey",
      "desc": "Options that specify how to unarchive and instantiate the nib."
    }
  ],
  "declaration": "@MainActor class UINib : NSObject",
  "inheritsFrom": [
    "NSObject"
  ]
}