{
  "path": "/documentation/appkit/nsdocument/saveoperationtype",
  "type": "Enumeration",
  "name": "NSDocument.SaveOperationType",
  "desc": "Constants for specifying the type of document-save operation to perform.",
  "items": [
    {
      "name": "case saveOperation",
      "desc": "An operation that overwrites a document’s file or file package with the document’s contents."
    },
    {
      "name": "case saveAsOperation",
      "desc": "An operation that writes the document’s contents to a new location and updates the document to point to that location"
    },
    {
      "name": "case saveToOperation",
      "desc": "An operation that writes a copy of the document's contents to the specified location, without changing the original document’s location."
    },
    {
      "name": "case autosaveElsewhereOperation",
      "desc": "An operation that writes an autosave version of the file to a different location."
    },
    {
      "name": "case autosaveInPlaceOperation",
      "desc": "An operation that overwrites the document’s current contents with autosave data."
    },
    {
      "name": "case autosaveAsOperation",
      "desc": "An operation that writes a document’s contents to a new file or file package even though the user has not explicitly requested it, then changes the document’s current location to point to the just-written file or file package."
    }
  ],
  "declaration": "enum SaveOperationType : UInt, @unchecked Sendable",
  "conformsTo": [
    "Sendable"
  ]
}