{
  "path": "/documentation/appkit/nsaccessibility/parameterizedattribute/1532391-layoutpointforscreenpoint",
  "type": "Type Property",
  "name": "layoutPointForScreenPoint",
  "desc": "The point in the layout area (NSValue) corresponding to the specified point on the screen (NSValue).DeprecatedUse of these constants is discouraged. Use the new method-based API instead. For more information, see Accessibility Programming Guide for OS X or NSAccessibilityProtocol.",
  "items": [],
  "declaration": "static let layoutPointForScreenPoint: NSAccessibility.ParameterizedAttribute"
}