{
  "path": "/documentation/uikit/nstextlayoutorientationprovider",
  "type": "Protocol",
  "name": "NSTextLayoutOrientationProvider",
  "desc": "A set of methods that define the orientation of text for an object.",
  "items": [
    {
      "name": "var layoutOrientation: NSLayoutManager.TextLayoutOrientation",
      "desc": "The default layout orientation."
    },
    {
      "name": "enum NSLayoutManager.TextLayoutOrientation",
      "desc": "Constants that describe the text layout orientation."
    }
  ],
  "declaration": "protocol NSTextLayoutOrientationProvider"
}