{
  "path": "/documentation/imagecapturecore/icscannerfeature",
  "type": "Class",
  "name": "ICScannerFeature",
  "desc": "An abstract class that describes a scanner feature.",
  "items": [
    {
      "name": "var humanReadableName: String?"
    },
    {
      "name": "var internalName: String?"
    },
    {
      "name": "var tooltip: String?"
    },
    {
      "name": "var type: ICScannerFeatureType"
    }
  ],
  "declaration": "class ICScannerFeature : NSObject",
  "inheritsFrom": [
    "NSObject"
  ]
}