{
  "path": "/documentation/metalperformanceshadersgraph/mpsgraph/3763058-sparsetensor",
  "type": "Instance Method",
  "name": "sparseTensor(sparseTensorWithType:tensors:shape:dataType:name:)",
  "desc": "No overview available.",
  "items": [],
  "declaration": "func sparseTensor(sparseTensorWithType sparseStorageType: MPSGraphSparseStorageType, \n          tensors inputTensorArray: [MPSGraphTensor], \n            shape: [NSNumber], \n         dataType: MPSDataType, \n             name: String?) -> MPSGraphTensor"
}