{
  "path": "/documentation/audiotoolbox/auparametereventtype",
  "type": "Enumeration",
  "name": "AUParameterEventType",
  "desc": "Audio unit parameter event types.",
  "items": [
    {
      "name": "case parameterEvent_Immediate",
      "desc": "An immediate change from the parameter’s previous value to a new value."
    },
    {
      "name": "case parameterEvent_Ramped",
      "desc": "A gradual change from the parameter’s previous value to a new value, applied linearly over a specified period of time"
    }
  ],
  "declaration": "enum AUParameterEventType : UInt32, @unchecked Sendable",
  "conformsTo": [
    "Sendable"
  ]
}