{
  "path": "/documentation/corefoundation/cfcharactersetpredefinedset",
  "type": "Enumeration",
  "name": "CFCharacterSetPredefinedSet",
  "desc": "Defines a predefined character set.",
  "items": [
    {
      "name": "case alphaNumeric",
      "desc": "Alpha Numeric character set (Unicode General Category L*, M*, & N*)."
    },
    {
      "name": "case capitalizedLetter",
      "desc": "Titlecase character set (Unicode General Category Lt)."
    },
    {
      "name": "case control",
      "desc": "Control character set (Unicode General Category Cc and Cf)."
    },
    {
      "name": "case decimalDigit",
      "desc": "Decimal digit character set."
    },
    {
      "name": "case decomposable",
      "desc": "Canonically decomposable character set."
    },
    {
      "name": "case illegal",
      "desc": "Illegal character set."
    },
    {
      "name": "case letter",
      "desc": "Letter character set (Unicode General Category L* & M*)."
    },
    {
      "name": "case lowercaseLetter",
      "desc": "Lowercase character set (Unicode General Category Ll)."
    },
    {
      "name": "case newline",
      "desc": "Newline character set (U000A ~ U000D, U0085, U2028, and U2029)."
    },
    {
      "name": "case nonBase",
      "desc": "Non-base character set (Unicode General Category M*)."
    },
    {
      "name": "case punctuation",
      "desc": "Punctuation character set (Unicode General Category P*)."
    },
    {
      "name": "case symbol",
      "desc": "Symbol character set (Unicode General Category S*)."
    },
    {
      "name": "case uppercaseLetter",
      "desc": "Uppercase character set (Unicode General Category Lu and Lt)."
    },
    {
      "name": "case whitespace",
      "desc": "Whitespace character set (Unicode General Category Zs and U0009 CHARACTER TABULATION)."
    },
    {
      "name": "case whitespaceAndNewline",
      "desc": "Whitespace and Newline character set (Unicode General Category Z*, U000A ~ U000D, and U0085)."
    }
  ],
  "declaration": "enum CFCharacterSetPredefinedSet, @unchecked Sendable",
  "conformsTo": [
    "Sendable"
  ]
}