{
  "path": "/documentation/fileprovider/nsfileprovidermanager/disconnectionoptions",
  "type": "Structure",
  "name": "NSFileProviderManager.DisconnectionOptions",
  "desc": "Options for disconnecting a domain from the extension.",
  "items": [
    {
      "name": "static var temporary: NSFileProviderManager.DisconnectionOptions",
      "desc": "A temporary disconnection."
    },
    {
      "name": "init(rawValue: UInt)",
      "desc": "Initializes the options from the raw value."
    }
  ],
  "declaration": "struct DisconnectionOptions, @unchecked Sendable",
  "conformsTo": [
    "OptionSet",
    "Sendable"
  ]
}