{
  "path": "/documentation/metalkit/mtktextureloader/origin",
  "type": "Structure",
  "name": "MTKTextureLoader.Origin",
  "desc": "Options for specifying when to flip the pixel coordinates of the texture.",
  "items": [
    {
      "name": "init(rawValue: String)",
      "desc": "Creates a texture origin option from a raw string value."
    },
    {
      "name": "static let topLeft: MTKTextureLoader.Origin",
      "desc": "An option for specifying images that should be flipped only to put their origin in the top-left corner."
    },
    {
      "name": "static let bottomLeft: MTKTextureLoader.Origin",
      "desc": "An option for specifying images that should be flipped only to put their origin in the bottom-left corner."
    },
    {
      "name": "static let flippedVertically: MTKTextureLoader.Origin",
      "desc": "An option that specifies that images should always be flipped."
    }
  ],
  "declaration": "struct Origin, @unchecked Sendable",
  "conformsTo": [
    "Equatable",
    "Hashable",
    "RawRepresentable",
    "Sendable"
  ]
}