{
  "path": "/documentation/passkit/pksuicapassproperties",
  "type": "Class",
  "name": "PKSuicaPassProperties",
  "desc": "The properties of a pass used as a ticket for the Suica transportation system.",
  "items": [
    {
      "name": "init?(for: PKPass)",
      "desc": "Instantiates a Suica pass properties object that contains the properties supported in the specified pass."
    },
    {
      "name": "var isBlocked: Bool",
      "desc": "A Boolean value that indicates whether the pass issuer disabled the pass."
    },
    {
      "name": "var isBlacklisted: Bool",
      "desc": "A Boolean value that indicates whether the transit pass issuer disabled the pass."
    },
    {
      "name": "var isGreenCarTicketUsed: Bool",
      "desc": "A Boolean value that indicates whether the customer has redeemed the Green Car ticket."
    },
    {
      "name": "var isInShinkansenStation: Bool",
      "desc": "A Boolean value that indicates whether the pass has tapped in at a Shinkansen Station and has not tapped out."
    },
    {
      "name": "var isInStation: Bool",
      "desc": "A Boolean value that indicates whether the transit pass has tapped in at a station and has not tapped out."
    },
    {
      "name": "var transitBalance: NSDecimalNumber",
      "desc": "The current usable stored value on the transit card."
    },
    {
      "name": "var transitBalanceCurrencyCode: String",
      "desc": "The currency code associated with the balance on the pass."
    },
    {
      "name": "var isBalanceAllowedForCommute: Bool",
      "desc": "A Boolean value that indicates how the balance can be used."
    },
    {
      "name": "var isLowBalanceGateNotificationEnabled: Bool",
      "desc": "A Boolean value that determines whether the terminal provides feedback if the balance is low after a deduction."
    }
  ],
  "declaration": "class PKSuicaPassProperties : PKTransitPassProperties",
  "inheritsFrom": [
    "PKTransitPassProperties"
  ]
}