{
  "path": "/documentation/quicklookthumbnailing/qlthumbnailgenerator/3153142-generatebestrepresentation",
  "type": "Instance Method",
  "name": "generateBestRepresentation(for:completion:)",
  "desc": "Generates the best possible thumbnail representation for a file and calls a handler upon completion.",
  "items": [],
  "declaration": "func generateBestRepresentation(for request: QLThumbnailGenerator.Request, \n                     completion completionHandler: @escaping (QLThumbnailRepresentation?, Error?) -> Void)"
}