{
  "path": "/documentation/virtualization/vzmacaddress",
  "type": "Class",
  "name": "VZMACAddress",
  "desc": "The media access control (MAC) address for a network interface in your virtual machine.",
  "items": [
    {
      "name": "class func randomLocallyAdministered() -> Self",
      "desc": "Returns a valid, random, locally administered, unicast MAC address."
    },
    {
      "name": "init?(string: String)",
      "desc": "Creates a MAC address object from a specially formatted string."
    },
    {
      "name": "init(ethernetAddress: ether_addr_t)",
      "desc": "Creates a MAC address from the specified 48-bit Ethernet address."
    },
    {
      "name": "var string: String",
      "desc": "The MAC address as a formatted string."
    },
    {
      "name": "var ethernetAddress: ether_addr_t",
      "desc": "The MAC address as an Ethernet data structure."
    },
    {
      "name": "var isBroadcastAddress: Bool",
      "desc": "A Boolean value that indicates whether the address is a broadcast address."
    },
    {
      "name": "var isMulticastAddress: Bool",
      "desc": "A Boolean value that indicates whether the address is a multicast address."
    },
    {
      "name": "var isUnicastAddress: Bool",
      "desc": "A Boolean value that indicates whether the address is a unicast address."
    },
    {
      "name": "var isLocallyAdministeredAddress: Bool",
      "desc": "A Boolean value that indicates whether the address is a locally administered address (LAA)."
    },
    {
      "name": "var isUniversallyAdministeredAddress: Bool",
      "desc": "A Boolean value that indicates whether the address is a universally adminstered address (UAA)."
    }
  ],
  "declaration": "class VZMACAddress : NSObject",
  "inheritsFrom": [
    "NSObject"
  ],
  "conformsTo": [
    "NSCopying"
  ]
}