{
  "path": "/documentation/realitykit/custommaterial/basecolor",
  "type": "Structure",
  "name": "CustomMaterial.BaseColor",
  "desc": "An object that defines an entity’s base color.",
  "items": [
    {
      "name": "init(tint: UIColor, texture: CustomMaterial.Texture?)",
      "desc": "Creates a base color object from a color or texture on iOS."
    },
    {
      "name": "init(tint: NSColor, texture: CustomMaterial.Texture?)",
      "desc": "Creates a base color object from a color or texture on macOS."
    },
    {
      "name": "init(PhysicallyBasedMaterial.BaseColor)",
      "desc": "Creates a custom base color object from an existing physically based material’s base color object."
    },
    {
      "name": "var texture: CustomMaterial.Texture?",
      "desc": "The base color as a UV-mapped image."
    },
    {
      "name": "var tint: NSColor"
    },
    {
      "name": "var tint: UIColor"
    }
  ],
  "declaration": "struct BaseColor"
}