{
  "path": "/documentation/sirikit/inappendtonoteintenthandling/2873750-resolvecontent",
  "type": "Instance Method",
  "name": "resolveContent(for:with:)",
  "desc": "Resolves the content to append to the note.DeprecatedThis intent is no longer available. You may define a custom intent instead. For more information, see Deprecated SiriKit Intent Domains.",
  "items": [],
  "declaration": "optional func resolveContent(for intent: INAppendToNoteIntent, \n                        with completion: @escaping (INNoteContentResolutionResult) -> Void)"
}