{
  "path": "/documentation/swift_packages/package",
  "type": "Class",
  "name": "Package",
  "desc": "The configuration of a Swift package.",
  "items": [
    {
      "name": "init(name: String, defaultLocalization: LanguageTag?, platforms: [SupportedPlatform]?, pkgConfig: String?, providers: [SystemPackageProvider]?, products: [Product], dependencies: [Package.Dependency], targets: [Target], swiftLanguageVersions: [SwiftVersion]?, cLanguageStandard: CLanguageStandard?, cxxLanguageStandard: CXXLanguageStandard?)",
      "desc": "Initializes a Swift package with configuration options you provide."
    },
    {
      "name": "var name: String",
      "desc": "The name of the Swift package."
    },
    {
      "name": "var defaultLocalization: LanguageTag?",
      "desc": "The default localization for resources."
    },
    {
      "name": "struct LanguageTag",
      "desc": "A wrapper around an IETF language tag."
    },
    {
      "name": "var products: [Product]",
      "desc": "The list of products that this package vends and that clients can use."
    },
    {
      "name": "class Product",
      "desc": "The object that defines a package product."
    },
    {
      "name": "var targets: [Target]",
      "desc": "The list of targets that are part of this package."
    },
    {
      "name": "class Target",
      "desc": "A target, the basic building block of a Swift package."
    },
    {
      "name": "var platforms: [SupportedPlatform]?",
      "desc": "The list of platforms supported by this package."
    },
    {
      "name": "struct SupportedPlatform",
      "desc": "A platform that the Swift package supports."
    },
    {
      "name": "struct Platform",
      "desc": "A platform that usually corresponds to an operating system such as iOS, macOS, or Linux."
    },
    {
      "name": "enum SystemPackageProvider",
      "desc": "The system package providers used in this Swift package."
    },
    {
      "name": "var pkgConfig: String?",
      "desc": "The name to use for C modules."
    },
    {
      "name": "var providers: [SystemPackageProvider]?",
      "desc": "An array of providers for the system target."
    },
    {
      "name": "var dependencies: [Package.Dependency]",
      "desc": "The list of package dependencies."
    },
    {
      "name": "class Package.Dependency",
      "desc": "A package dependency of a Swift package."
    },
    {
      "name": "enum SwiftVersion",
      "desc": "The version of the Swift language to use for compiling Swift sources in the package."
    },
    {
      "name": "enum CLanguageStandard",
      "desc": "The supported C language standard to use for compiling C sources in the package."
    },
    {
      "name": "enum CXXLanguageStandard",
      "desc": "The supported C++ language standards to use for compiling C++ sources in the package."
    },
    {
      "name": "var swiftLanguageVersions: [SwiftVersion]?",
      "desc": "The list of Swift versions that this package is compatible with."
    },
    {
      "name": "var cLanguageStandard: CLanguageStandard?",
      "desc": "The C language standard to use for all C targets in this package."
    },
    {
      "name": "var cxxLanguageStandard: CXXLanguageStandard?",
      "desc": "The C++ language standard to use for all C++ targets in this package."
    },
    {
      "name": "func encode(to: Encoder)",
      "desc": "Encodes this value into the given encoder."
    }
  ],
  "declaration": "final class Package",
  "conformsTo": [
    "Encodable"
  ]
}