{
  "path": "/documentation/network/nwprotocolwebsocket",
  "type": "Class",
  "name": "NWProtocolWebSocket",
  "desc": "A network protocol for connections that use WebSocket.",
  "items": [
    {
      "name": "class NWProtocolWebSocket.Options",
      "desc": "A container of options for configuring how WebSocket is used on a connection."
    },
    {
      "name": "static let definition: NWProtocolDefinition",
      "desc": "The system definition of the WebSocket protocol."
    },
    {
      "name": "class NWProtocolWebSocket.Metadata",
      "desc": "A WebSocket message you configure when sending and receiving packets."
    }
  ],
  "declaration": "class NWProtocolWebSocket : NWProtocol",
  "inheritsFrom": [
    "NWProtocol"
  ]
}