{
  "path": "/documentation/applemusicapi/applecurators/attributes",
  "type": "Object",
  "name": "AppleCurators.Attributes",
  "desc": "The attributes for an Apple curator resource.",
  "items": [
    {
      "name": "artwork",
      "desc": "The curator artwork."
    },
    {
      "name": "editorialNotes",
      "desc": "The notes about the curator that appear in the Apple Music catalog."
    },
    {
      "name": "kind",
      "desc": "The type of curator. Possible values are:Curator: An individual curator entity.Genre: A curator that represents a cohesive music genre.Show: A curator associated with a particular Apple Music show."
    },
    {
      "name": "name",
      "desc": "The localized name of the curator."
    },
    {
      "name": "shortName",
      "desc": "The localized shortened name of the curator."
    },
    {
      "name": "showHostName",
      "desc": "The name of the host if kind is Show."
    },
    {
      "name": "url",
      "desc": "The URL for sharing the curator in Apple Music."
    }
  ]
}