{
  "path": "/documentation/avfaudio/avmusicsequenceloadoptions",
  "type": "Structure",
  "name": "AVMusicSequenceLoadOptions",
  "desc": "A structure that defines whether data on different MIDI channels map to multiple tracks, or whether the framework preserves the tracks as they are.",
  "items": [
    {
      "name": "init(rawValue: UInt)",
      "desc": "Creates a new instance with the raw value you specify."
    },
    {
      "name": "static var smf_ChannelsToTracks: AVMusicSequenceLoadOptions",
      "desc": "An option that represents data on different MIDI channels mapped to multiple tracks."
    }
  ],
  "declaration": "struct AVMusicSequenceLoadOptions, @unchecked Sendable",
  "conformsTo": [
    "OptionSet",
    "Sendable"
  ]
}