{
  "path": "/documentation/coregraphics/cglinejoin",
  "type": "Enumeration",
  "name": "CGLineJoin",
  "desc": "Junction types for stroked lines.",
  "items": [
    {
      "name": "case miter"
    },
    {
      "name": "case round",
      "desc": "A join with a rounded end. Core Graphics draws the line to extend beyond the endpoint of the path. The line ends with a semicircular arc with a radius of 1/2 the line’s width, centered on the endpoint."
    },
    {
      "name": "case bevel",
      "desc": "A join with a squared-off end. Core Graphics draws the line to extend beyond the endpoint of the path, for a distance of 1/2 the line’s width."
    }
  ],
  "declaration": "enum CGLineJoin : Int32, @unchecked Sendable",
  "conformsTo": [
    "Sendable"
  ]
}