{
  "path": "/documentation/xctest/xcuikeyboardkey",
  "type": "Structure",
  "name": "XCUIKeyboardKey",
  "desc": "Constants to represent keys that have no typewritten equivalent.",
  "items": [
    {
      "name": "static let command: XCUIKeyboardKey",
      "desc": "A constant that represents the Command key."
    },
    {
      "name": "static let control: XCUIKeyboardKey",
      "desc": "A constant that represents the Control key."
    },
    {
      "name": "static let option: XCUIKeyboardKey",
      "desc": "A constant that represents the Option key."
    },
    {
      "name": "static let shift: XCUIKeyboardKey",
      "desc": "A constant that represents the Shift key."
    },
    {
      "name": "static let rightCommand: XCUIKeyboardKey",
      "desc": "A constant that represents the right Command key."
    },
    {
      "name": "static let rightControl: XCUIKeyboardKey",
      "desc": "A constant that represents the right Control key."
    },
    {
      "name": "static let rightOption: XCUIKeyboardKey",
      "desc": "A constant that represents the right Option key."
    },
    {
      "name": "static let rightShift: XCUIKeyboardKey",
      "desc": "A constant that represents the right Shift key."
    },
    {
      "name": "static let upArrow: XCUIKeyboardKey",
      "desc": "A constant that represents the Up Arrow key."
    },
    {
      "name": "static let downArrow: XCUIKeyboardKey",
      "desc": "A constant that represents the Down Arrow key."
    },
    {
      "name": "static let leftArrow: XCUIKeyboardKey",
      "desc": "A constant that represents the Left Arrow key."
    },
    {
      "name": "static let rightArrow: XCUIKeyboardKey",
      "desc": "A constant that represents the Right Arrow key."
    },
    {
      "name": "static let home: XCUIKeyboardKey",
      "desc": "A constant that represents the Home key."
    },
    {
      "name": "static let end: XCUIKeyboardKey",
      "desc": "A constant that represents the End key."
    },
    {
      "name": "static let pageUp: XCUIKeyboardKey",
      "desc": "A constant that represents the Page Up key."
    },
    {
      "name": "static let pageDown: XCUIKeyboardKey",
      "desc": "A constant that represents the Page Down key."
    },
    {
      "name": "static let help: XCUIKeyboardKey",
      "desc": "A constant that represents the Help key."
    },
    {
      "name": "static let secondaryFn: XCUIKeyboardKey",
      "desc": "A constant that represents the Fn (Function) key."
    },
    {
      "name": "static let F1: XCUIKeyboardKey",
      "desc": "A constant that represents the F1 key."
    },
    {
      "name": "static let F2: XCUIKeyboardKey",
      "desc": "A constant that represents the F2 key."
    },
    {
      "name": "static let F3: XCUIKeyboardKey",
      "desc": "A constant that represents the F3 key."
    },
    {
      "name": "static let F4: XCUIKeyboardKey",
      "desc": "A constant that represents the F4 key."
    },
    {
      "name": "static let F5: XCUIKeyboardKey",
      "desc": "A constant that represents the F5 key."
    },
    {
      "name": "static let F6: XCUIKeyboardKey",
      "desc": "A constant that represents the F6 key."
    },
    {
      "name": "static let F7: XCUIKeyboardKey",
      "desc": "A constant that represents the F7 key."
    },
    {
      "name": "static let F8: XCUIKeyboardKey",
      "desc": "A constant that represents the F8 key."
    },
    {
      "name": "static let F9: XCUIKeyboardKey",
      "desc": "A constant that represents the F9 key."
    },
    {
      "name": "static let F10: XCUIKeyboardKey",
      "desc": "A constant that represents the F10 key."
    },
    {
      "name": "static let F11: XCUIKeyboardKey",
      "desc": "A constant that represents the F11 key."
    },
    {
      "name": "static let F12: XCUIKeyboardKey",
      "desc": "A constant that represents the F12 key."
    },
    {
      "name": "static let F13: XCUIKeyboardKey",
      "desc": "A constant that represents the F13 key."
    },
    {
      "name": "static let F14: XCUIKeyboardKey",
      "desc": "A constant that represents the F14 key."
    },
    {
      "name": "static let F15: XCUIKeyboardKey",
      "desc": "A constant that represents the F15 key."
    },
    {
      "name": "static let F16: XCUIKeyboardKey",
      "desc": "A constant that represents the F16 key."
    },
    {
      "name": "static let F17: XCUIKeyboardKey",
      "desc": "A constant that represents the F17 key."
    },
    {
      "name": "static let F18: XCUIKeyboardKey",
      "desc": "A constant that represents the F18 key."
    },
    {
      "name": "static let F19: XCUIKeyboardKey",
      "desc": "A constant that represents the F19 key."
    },
    {
      "name": "static let capsLock: XCUIKeyboardKey",
      "desc": "A constant that represents the Caps Lock key."
    },
    {
      "name": "static let delete: XCUIKeyboardKey",
      "desc": "A constant that represents the Delete key."
    },
    {
      "name": "static let forwardDelete: XCUIKeyboardKey",
      "desc": "A constant that represents the Forward Delete key."
    },
    {
      "name": "static let space: XCUIKeyboardKey",
      "desc": "A constant that represents the Space bar."
    },
    {
      "name": "static let tab: XCUIKeyboardKey",
      "desc": "A constant that represents the Tab key."
    },
    {
      "name": "static let clear: XCUIKeyboardKey",
      "desc": "A constant that represents the Clear key."
    },
    {
      "name": "static let enter: XCUIKeyboardKey",
      "desc": "A constant that represents the Enter key."
    },
    {
      "name": "static let escape: XCUIKeyboardKey",
      "desc": "A constant that represents the Esc (Escape) key."
    },
    {
      "name": "static let `return`: XCUIKeyboardKey",
      "desc": "A constant that represents the Return key."
    },
    {
      "name": "init(String)",
      "desc": "Initializes a constant with a string that represents a keyboard key."
    },
    {
      "name": "init(rawValue: String)",
      "desc": "Initializes a constant with a string that represents a keyboard key."
    }
  ],
  "declaration": "struct XCUIKeyboardKey, @unchecked Sendable",
  "conformsTo": [
    "Equatable",
    "Hashable",
    "RawRepresentable",
    "Sendable"
  ]
}