{
  "path": "/documentation/scenekit/scnpyramid",
  "type": "Class",
  "name": "SCNPyramid",
  "desc": "A right rectangular pyramid geometry.",
  "items": [
    {
      "name": "init(width: CGFloat, height: CGFloat, length: CGFloat)",
      "desc": "Creates a pyramid geometry with the specified width, height, and length."
    },
    {
      "name": "var width: CGFloat",
      "desc": "The extent of the pyramid along its x-axis. Animatable."
    },
    {
      "name": "var height: CGFloat",
      "desc": "The extent of the pyramid along its y-axis. Animatable."
    },
    {
      "name": "var length: CGFloat",
      "desc": "The extent of the pyramid along its z-axis. Animatable."
    },
    {
      "name": "var widthSegmentCount: Int",
      "desc": "The number of subdivisions in each face of the pyramid along its x-axis. Animatable."
    },
    {
      "name": "var heightSegmentCount: Int",
      "desc": "The number of subdivisions in each face of the pyramid along its y-axis. Animatable."
    },
    {
      "name": "var lengthSegmentCount: Int",
      "desc": "The number of subdivisions in each face of the pyramid along its z-axis. Animatable."
    }
  ],
  "declaration": "class SCNPyramid : SCNGeometry",
  "inheritsFrom": [
    "SCNGeometry"
  ]
}