{
  "path": "/documentation/watchkit/wkbackgroundfetchresult",
  "type": "Enumeration",
  "name": "WKBackgroundFetchResult",
  "desc": "The result of an attempt to download the content associated with a remote notification.",
  "items": [
    {
      "name": "case failed",
      "desc": "The download attempt failed."
    },
    {
      "name": "case newData",
      "desc": "The download attempt succeeded."
    },
    {
      "name": "case noData",
      "desc": "The notification has no associated content."
    }
  ],
  "declaration": "enum WKBackgroundFetchResult : UInt, @unchecked Sendable",
  "conformsTo": [
    "Sendable"
  ]
}