{
  "path": "/documentation/clockkit/clkwatchfacelibrary/errorcode",
  "type": "Enumeration",
  "name": "CLKWatchFaceLibrary.ErrorCode",
  "desc": "Error codes that the watch face library returns.",
  "items": [
    {
      "name": "case notFileURL",
      "desc": "No file was found at the specified URL."
    },
    {
      "name": "case invalidFile",
      "desc": "The specified file wasn’t a valid watch face file."
    },
    {
      "name": "case permissionDenied",
      "desc": "The app does not have permission to read the specified file."
    },
    {
      "name": "case faceNotAvailable",
      "desc": "The watch face is not available on this device."
    }
  ],
  "declaration": "enum ErrorCode : Int, @unchecked Sendable",
  "conformsTo": [
    "Sendable"
  ]
}