{
  "path": "/documentation/pdfkit/pdfannotationlineendingstyle",
  "type": "Structure",
  "name": "PDFAnnotationLineEndingStyle",
  "desc": "No overview available.",
  "items": [
    {
      "name": "static let circle: PDFAnnotationLineEndingStyle",
      "desc": "A style that displays a circle line ending and fills it with the annotation’s interior color."
    },
    {
      "name": "static let closedArrow: PDFAnnotationLineEndingStyle",
      "desc": "A style that displays a closed arrowhead line ending and fills it with the annotation’s interior color."
    },
    {
      "name": "static let diamond: PDFAnnotationLineEndingStyle"
    },
    {
      "name": "static let none: PDFAnnotationLineEndingStyle"
    },
    {
      "name": "static let openArrow: PDFAnnotationLineEndingStyle",
      "desc": "A style that displays an open arrowhead line ending."
    },
    {
      "name": "static let square: PDFAnnotationLineEndingStyle",
      "desc": "A style that displays a square line ending and fills it with the annotation’s interior color."
    },
    {
      "name": "init(rawValue: String)",
      "desc": "Creates a line-ending style using the specified raw string value."
    }
  ],
  "declaration": "struct PDFAnnotationLineEndingStyle, @unchecked Sendable",
  "conformsTo": [
    "Equatable",
    "Hashable",
    "RawRepresentable",
    "Sendable"
  ]
}