{
  "path": "/documentation/clockkit/clkcomplicationtemplateutilitariansmallflat",
  "type": "Class",
  "name": "CLKComplicationTemplateUtilitarianSmallFlat",
  "desc": "A template for displaying an image and text in a single line.",
  "items": [
    {
      "name": "init(textProvider: CLKTextProvider)",
      "desc": "Creates a new template that has a single line of text."
    },
    {
      "name": "init(textProvider: CLKTextProvider, imageProvider: CLKImageProvider?)",
      "desc": "Creates a new template that has a single row with an image and a line of text."
    },
    {
      "name": "var imageProvider: CLKImageProvider?",
      "desc": "The image to display."
    },
    {
      "name": "var textProvider: CLKTextProvider",
      "desc": "The text to display."
    }
  ],
  "declaration": "class CLKComplicationTemplateUtilitarianSmallFlat : CLKComplicationTemplate",
  "inheritsFrom": [
    "CLKComplicationTemplate"
  ]
}