{
  "path": "/documentation/iobluetoothui/iobluetoothdeviceselectorcontroller",
  "type": "Class",
  "name": "IOBluetoothDeviceSelectorController",
  "desc": "A NSWindowController subclass to display a window to initiate pairing to other bluetooth devices.",
  "items": [
    {
      "name": "func addAllowedUUID(IOBluetoothSDPUUID!)",
      "desc": "Adds a UUID to the list of UUIDs that are used to validate the user's selection."
    },
    {
      "name": "func addAllowedUUIDArray([Any]!)",
      "desc": "Adds an array of UUIDs to the list of UUIDs that are used to validate the user's selection."
    },
    {
      "name": "func beginSheetModal(for: NSWindow!, modalDelegate: Any!, didEnd: Selector!, contextInfo: UnsafeMutableRawPointer!) -> IOReturn",
      "desc": "Runs the device selector panel as a sheet on the target window."
    },
    {
      "name": "func clearAllowedUUIDs()",
      "desc": "Resets the controller back to the default state where it will accept any device the user selects."
    },
    {
      "name": "func getCancel() -> String!",
      "desc": "Returns the title of the default/cancel button in the device selector panel."
    },
    {
      "name": "func getDescriptionText() -> String!",
      "desc": "Returns the description text that appears in the device selector panel."
    },
    {
      "name": "func getHeader() -> String!",
      "desc": "Returns the header text that appears in the device selector panel."
    },
    {
      "name": "func getOptions() -> IOBluetoothServiceBrowserControllerOptions",
      "desc": "Returns the option bits that control the panel's behavior."
    },
    {
      "name": "func getPrompt() -> String!",
      "desc": "Returns the title of the default/select button in the device selector panel."
    },
    {
      "name": "func getResults() -> [Any]!",
      "desc": "Returns the result of the user's selection."
    },
    {
      "name": "func getSearchAttributes() -> UnsafePointer<IOBluetoothDeviceSearchAttributes>!",
      "desc": "Returns the search attributes that control the panel's search/inquiry behavior."
    },
    {
      "name": "func getTitle() -> String!",
      "desc": "Returns the title of the device selector panel."
    },
    {
      "name": "func runModal() -> Int32",
      "desc": "Runs the device selector panel in a modal session to allow the user to select a Bluetooth device."
    },
    {
      "name": "func setCancel(String!)",
      "desc": "Sets the title of the default/cancel button in the device selector panel."
    },
    {
      "name": "func setDescriptionText(String!)",
      "desc": "Sets the description text that appears in the device selector panel."
    },
    {
      "name": "func setHeader(String!)",
      "desc": "Sets the header text that appears in the device selector panel."
    },
    {
      "name": "func setOptions(IOBluetoothServiceBrowserControllerOptions)",
      "desc": "Sets the option bits that control the panel's behavior."
    },
    {
      "name": "func setPrompt(String!)",
      "desc": "Sets the title of the default/select button in the device selector panel."
    },
    {
      "name": "func setSearchAttributes(UnsafePointer<IOBluetoothDeviceSearchAttributes>!)",
      "desc": "Sets the search attributes that control the panel's search/inquiry behavior."
    },
    {
      "name": "func setTitle(String!)",
      "desc": "Sets the title of the panel when not run as a sheet."
    },
    {
      "name": "class func deviceSelector() -> IOBluetoothDeviceSelectorController!"
    }
  ],
  "declaration": "class IOBluetoothDeviceSelectorController : NSWindowController",
  "inheritsFrom": [
    "NSWindowController"
  ]
}